{
  "schema_version": "1.0",
  "id": "risk",
  "kind": "lens",
  "display_name": "Risk",
  "prompt_path": "reviews/lenses/lens-risk.md",
  "domain_focus": [
    "failure modes",
    "rollback",
    "observability",
    "deployment risk",
    "blast radius"
  ],
  "cross_cutting_ownership": {
    "primary": [
      "Reliability / rollback",
      "Observability / debuggability"
    ],
    "secondary": []
  },
  "selection_domains": ["migration-and-data", "operational-risk"],
  "advisory_tool_expectations": [
    "Read the target plan or spec directly from disk.",
    "Inspect referenced rollout, observability, recovery, or operations docs when provided.",
    "Separate material ship risks from theoretical risks."
  ]
}
